datannurpy/__init__.py
datannurpy/add_database.py
datannurpy/add_dataset.py
datannurpy/add_folder.py
datannurpy/add_metadata.py
datannurpy/catalog.py
datannurpy/py.typed
datannurpy/app/.htaccess
datannurpy/app/.nojekyll
datannurpy/app/CHANGELOG.md
datannurpy/app/LICENSE
datannurpy/app/README.md
datannurpy/app/index.html
datannurpy/app/manifest.json
datannurpy/app/package.json
datannurpy/app/tsconfig.json
datannurpy/app/api/.htaccess
datannurpy/app/api/api-docs-raw.html
datannurpy/app/api/api-docs.html
datannurpy/app/api/openapi-raw.json
datannurpy/app/api/openapi.json
datannurpy/app/api/llm/common.php
datannurpy/app/api/llm/index.php
datannurpy/app/api/llm/session.php
datannurpy/app/api/llm/status.php
datannurpy/app/api/llm/transcribe.php
datannurpy/app/api/nodejs/server.ts
datannurpy/app/api/php/JsonDatabase.php
datannurpy/app/api/php/Router.php
datannurpy/app/api/php/index.php
datannurpy/app/assets/browser-warning.js
datannurpy/app/assets/fa-solid-900-8GirhLYJ.woff2
datannurpy/app/assets/index-5-Z6ppWD.js
datannurpy/app/assets/index-5-Z6ppWD.js.map
datannurpy/app/assets/index-DYUAkZ4M.css
datannurpy/app/assets/main-banner-dark.png
datannurpy/app/assets/main-banner.png
datannurpy/app/assets/about-page/about-page-diagramm-dark.webp
datannurpy/app/assets/about-page/about-page-diagramm.webp
datannurpy/app/assets/about-page/dataset-histo-commune-preview-dark.webp
datannurpy/app/assets/about-page/dataset-histo-commune-preview.webp
datannurpy/app/assets/about-page/dataset-isco-mobile-dark.webp
datannurpy/app/assets/about-page/dataset-isco-mobile.webp
datannurpy/app/assets/about-page/dataset-list-histo-dark.webp
datannurpy/app/assets/about-page/dataset-list-histo.webp
datannurpy/app/assets/about-page/datasets-tab-filter-dark.webp
datannurpy/app/assets/about-page/datasets-tab-filter.webp
datannurpy/app/assets/about-page/doc-tourisme-dark.webp
datannurpy/app/assets/about-page/doc-tourisme.webp
datannurpy/app/assets/about-page/dossier-sitg-tab-dataset-dark.webp
datannurpy-0.4.0.dist-info/METADATA
datannurpy-0.4.0.dist-info/WHEEL
datannurpy-0.4.0.dist-info/licenses/LICENSE
datannurpy-0.4.0.dist-info/RECORD
