Metadata-Version: 2.4
Name: datannurpy
Version: 0.4.0
Summary: Python library for datannur catalog metadata management
Project-URL: Homepage, https://github.com/datannur/datannurpy
Project-URL: Repository, https://github.com/datannur/datannurpy
Project-URL: Documentation, https://github.com/datannur/datannurpy#readme
Project-URL: Issues, https://github.com/datannur/datannurpy/issues
Author: datannur
License: MIT
License-File: LICENSE
Classifier: Development Status :: 4 - Beta
Classifier: License :: OSI Approved :: MIT License
Classifier: Programming Language :: Python :: 3
Classifier: Programming Language :: Python :: 3.9
Classifier: Programming Language :: Python :: 3.10
Classifier: Programming Language :: Python :: 3.11
Classifier: Programming Language :: Python :: 3.12
Classifier: Programming Language :: Python :: 3.13
Classifier: Programming Language :: Python :: 3.14
Requires-Python: >=3.9
Requires-Dist: ibis-framework[duckdb]>=11.0
Requires-Dist: openpyxl>=3.0
Requires-Dist: typing-extensions>=4.0; python_version < '3.11'
Requires-Dist: xlrd>=2.0
Provides-Extra: databases
Requires-Dist: ibis-framework[mssql,mysql,oracle,postgres]>=11.0; extra == 'databases'
Provides-Extra: delta
Requires-Dist: deltalake>=0.18.0; extra == 'delta'
Provides-Extra: iceberg
Requires-Dist: pyiceberg>=0.10.0; extra == 'iceberg'
Provides-Extra: mssql
Requires-Dist: ibis-framework[mssql]>=11.0; extra == 'mssql'
Provides-Extra: mysql
Requires-Dist: ibis-framework[mysql]>=11.0; extra == 'mysql'
Provides-Extra: oracle
Requires-Dist: ibis-framework[oracle]>=11.0; extra == 'oracle'
Provides-Extra: postgres
Requires-Dist: ibis-framework[postgres]>=11.0; extra == 'postgres'
Provides-Extra: stat
Requires-Dist: pyreadstat<=1.2.8,>=1.2.0; (python_version < '3.10') and extra == 'stat'
Requires-Dist: pyreadstat>=1.2.0; (python_version >= '3.10') and extra == 'stat'
